chronostring/__init__.py
chronostring/chronostring.py
chronostring/interpreter.py
chronostring/processors.py
chronostring/processors_fr.py
chronostring/tokenizer.py
chronostring/tokens.py
chronostring/tokens_fr.py
chronostring/utils.py
chronostring-0.1.4.dist-info/licenses/AUTHORS.md
chronostring-0.1.4.dist-info/licenses/LICENSE
tests/__init__.py
tests/test_parser.py
chronostring-0.1.4.dist-info/METADATA
chronostring-0.1.4.dist-info/WHEEL
chronostring-0.1.4.dist-info/top_level.txt
chronostring-0.1.4.dist-info/RECORD
