Metadata-Version: 2.4
Name: chronostring
Version: 0.1.4
Summary: Extracts and structures dates and times from natural French text.
Home-page: https://forge.chapril.org/jmtrivial/chronostring
Author: Jean-Marie Favreau
Author-email: jeanmarie.favreau@free.fr
Classifier: Programming Language :: Python :: 3
Classifier: License :: OSI Approved :: GNU Affero General Public License v3
Requires-Python: >=3.7
License-File: LICENSE
License-File: AUTHORS.md
Dynamic: author
Dynamic: author-email
Dynamic: classifier
Dynamic: description
Dynamic: description-content-type
Dynamic: home-page
Dynamic: license-file
Dynamic: requires-python
Dynamic: summary
